binho/__init__.py
binho/accessory.py
binho/binhoHostAdapter.py
binho/device.py
binho/errors.py
binho/interface.py
binho/programmer.py
binho/utils.py
binho/version.py
binho/accessories/__init__.py
binho/commands/__init__.py
binho/commands/binho.py
binho/commands/binho_1wire.py
binho/commands/binho_adc.py
binho/commands/binho_custom.py
binho/commands/binho_dac.py
binho/commands/binho_daplink.py
binho/commands/binho_dfu.py
binho/commands/binho_eeprom.py
binho/commands/binho_flasher.py
binho/commands/binho_gpio.py
binho/commands/binho_i2c.py
binho/commands/binho_info.py
binho/commands/binho_pwm.py
binho/commands/binho_shell.py
binho/commands/binho_spi.py
binho/commands/binho_spiflash.py
binho/comms/__init__.py
binho/comms/comms.py
binho/comms/device.py
binho/comms/manager.py
binho/comms/drivers/__init__.py
binho/comms/drivers/core.py
binho/comms/drivers/i2c.py
binho/comms/drivers/io.py
binho/comms/drivers/onewire.py
binho/comms/drivers/spi.py
binho/comms/drivers/swi.py
binho/comms/drivers/uart.py
binho/devices/__init__.py
binho/devices/nova.py
binho/devices/protonovaSPI.py
binho/interfaces/__init__.py
binho/interfaces/adc.py
binho/interfaces/dac.py
binho/interfaces/gpio.py
binho/interfaces/i2cBus.py
binho/interfaces/i2cDevice.py
binho/interfaces/led.py
binho/interfaces/oneWireBus.py
binho/interfaces/oneWireDevice.py
binho/interfaces/spiBus.py
binho/interfaces/spiDevice.py
binho/interfaces/uart.py
binho/programmers/__init__.py
binho/programmers/eeprom.py
binho/programmers/spiFlash.py
binho/support/__init__.py
binho/support/bits.py
binho/util/__init__.py
binho/util/console.py
binho/util/interactive.py
binho/util/register.py
binho-1.0.9.dist-info/LICENSE
binho-1.0.9.dist-info/METADATA
binho-1.0.9.dist-info/WHEEL
binho-1.0.9.dist-info/entry_points.txt
binho-1.0.9.dist-info/top_level.txt
binho-1.0.9.dist-info/RECORD
