Metadata-Version: 2.1
Name: binho
Version: 1.0.9
Summary: Python package for Binho USB host adapter products
Home-page: https://binho.io
Author: Binho LLC
Author-email: support@binho.io
License: BSD
Platform: any
Classifier: Programming Language :: Python
Classifier: Development Status :: 1 - Planning
Classifier: Natural Language :: English
Classifier: Environment :: Console
Classifier: Environment :: Plugins
Classifier: Intended Audience :: Developers
Classifier: Intended Audience :: Science/Research
Classifier: License :: OSI Approved :: BSD License
Classifier: Operating System :: OS Independent
Classifier: Topic :: Scientific/Engineering
License-File: LICENSE
Requires-Dist: ipython
Requires-Dist: future
Requires-Dist: intelhex
Requires-Dist: pyserial
Requires-Dist: psutil
Requires-Dist: hidapi
Requires-Dist: requests
Provides-Extra: dev
Requires-Dist: sphinx ; extra == 'dev'
Requires-Dist: sphinx-rtd-theme ; extra == 'dev'
